kreuzbergml/__init__.py
kreuzbergml/code/__init__.py
kreuzbergml/config/__init__.py
kreuzbergml/config/logging.py
kreuzbergml/data/__init__.py
kreuzbergml/data/postgres.py
kreuzbergml/deployment/__init__.py
kreuzbergml/deployment/azure/__init__.py
kreuzbergml/deployment/azure/app.py
kreuzbergml/deployment/azure/database.py
kreuzbergml/model/__init__.py
kreuzbergml/model/param_factory.py
kreuzbergml/prototype/__init__.py
tests/__init__.py
tests/test_data_quality.py
kreuzbergml-0.1.3.dist-info/LICENSE
kreuzbergml-0.1.3.dist-info/METADATA
kreuzbergml-0.1.3.dist-info/WHEEL
kreuzbergml-0.1.3.dist-info/top_level.txt
kreuzbergml-0.1.3.dist-info/RECORD
